apache_airflow_providers_box-1.0.6.dist-info/METADATA
apache_airflow_providers_box-1.0.6.dist-info/WHEEL
apache_airflow_providers_box-1.0.6.dist-info/entry_points.txt
apache_airflow_providers_box-1.0.6.dist-info/licenses/LICENSE
apache_airflow_providers_box-1.0.6.dist-info/licenses/NOTICE
box_airflow_provider/__init__.py
box_airflow_provider/_version.txt
box_airflow_provider/hooks/__init__.py
box_airflow_provider/hooks/box.py
box_airflow_provider/models.py
box_airflow_provider/operators/__init__.py
box_airflow_provider/operators/box.py
box_airflow_provider/sensors/__init__.py
box_airflow_provider/sensors/box.py
box_airflow_provider/triggers/__init__.py
box_airflow_provider/triggers/box.py
box_airflow_provider/version.py
apache_airflow_providers_box-1.0.6.dist-info/RECORD
