Metadata-Version: 2.4
Name: apache-airflow-providers-box
Version: 1.0.6
Summary: Box.com provider for Apache Airflow.
Author-Email: Mikael Arvola <marvel@illinois.edu>
License-File: LICENSE
License-File: NOTICE
Classifier: Framework :: Apache Airflow
Classifier: Framework :: Apache Airflow :: Provider
Project-URL: Source, https://github.com/graduatecollege/apache-airflow-providers-box
Requires-Python: ~=3.12.0
Requires-Dist: apache-airflow<3,>=2.10.0
Requires-Dist: boxsdk>=10
